{
	"id": "HE-HORIZON-CL5-2026-03-D3-19",
	"titulo": "Affordable and sustainable primary equipment for Future-Ready multi-terminal HVDC Systems",
	"descricao": "Expected Outcome:Project results are expected to contribute to all the following expected outcomes:The expansion of High Voltage Direct Current (HVDC) infrastructure across Europe is facilitated and supports the EU's energy transition through more performant, sustainable and affordable HVDC equipment that ensure higher grid reliability and stability.Enhanced affordability and interoperability of HVDC grid equipment.Enhanced reliability and stability of HVDC Grid, through developing advanced prot",
	"fonte": "Horizon Europe",
	"programa": "Horizon Europe",
	"dataAbertura": "2025-12-18",
	"dataFecho": "2026-03-31",
	"montante": "126400029",
	"regiao": "Europa",
	"url": "https://ec.europa.eu/info/funding-tenders/opportunities/portal/screen/opportunities/topic-details/HORIZON-CL5-2026-03-D3-19",
	"status": "Aberto",
	"scrapedAt": "2025-12-12T16:55:46.406Z"
}